fabryc/__init__.py
fabryc/auth.py
fabryc/clients/__init__.py
fabryc/clients/rest/__init__.py
fabryc/clients/rest/base.py
fabryc/clients/rest/fabric.py
fabryc/clients/rest/powerbi.py
fabryc/clients/xmla.py
fabryc/main.py
fabryc/report.py
fabryc/semantic_model.py
fabryc/setup.py
fabryc/workspace.py
fabryc-0.1.1rc1.dist-info/LICENSE
fabryc-0.1.1rc1.dist-info/METADATA
fabryc-0.1.1rc1.dist-info/WHEEL
fabryc-0.1.1rc1.dist-info/RECORD
