Metadata-Version: 2.1
Name: fabryc
Version: 0.1.1rc1
Summary: Python API for Microsoft Fabric (Semantic Models, Reports...)
Home-page: https://github.com/lgrosjean/fabryc
License: MIT
Author: Léo Grosjean
Author-email: leo.grosjean@servier.com
Requires-Python: >=3.9,<3.13
Classifier: License :: OSI Approved :: MIT License
Classifier: Programming Language :: Python :: 3
Classifier: Programming Language :: Python :: 3.9
Classifier: Programming Language :: Python :: 3.10
Classifier: Programming Language :: Python :: 3.11
Classifier: Programming Language :: Python :: 3.12
Requires-Dist: azure-identity (>=1.15.0,<2.0.0)
Requires-Dist: pandas (>=2.2.1,<3.0.0)
Requires-Dist: pythonnet (>=3.0.3,<4.0.0)
Requires-Dist: requests (>=2.31.0,<3.0.0)
Project-URL: Repository, https://github.com/lgrosjean/fabryc
